{
  "D\u00e9sir\u00e9e-des-Anges": 18,
  "Villevieille": 10,
  "Bichkek": 9,
  "A": 8,
  "Sainte-Montagne": 6,
  "Paris": 5,
  "de-": 5,
  "Castille": 5,
  "Chicon": 4,
  "Sologne": 4,
  "Saint-Jean": 3,
  "Rome": 2,
  "Vierge": 2,
  "Bitche": 2,
  "en-": 2,
  "Tirande": 2,
  "Ville-": 2,
  "bres": 2,
  "M\u00e9lanie": 2,
  "Biblioth\u00e8que nationale de France\n\f\n11 Gallica\n\n \n\nAudoux": 1,
  "Biblioth\u00e8que nationale de France": 1,
  "Biblioth\u00e8que nationale de France\n\f\n8 MARIE-CLAIRE": 1,
  "Ilest": 1,
  "h\u00e9ppenr": 1,
  "Voulez": 1,
  "RER": 1,
  "LE ER RE": 1,
  "D": 1,
  "Coup": 1,
  "Ism\u00e9rie": 1,
  "m'\u2019assurant": 1,
  "paratifs": 1,
  "au\u2019": 1,
  "PR": 1,
  "surun": 1,
  "brassa": 1,
  "Saintes": 1,
  "\u00c6leva": 1,
  "abaiss": 1,
  "cognac": 1,
  "Unpeuavantl'": 1,
  "Acheminer l'Orgueilleuse": 1,
  "Acheminer la B\u00eate": 1,
  "E": 1,
  "Ch\u00e2taigniers": 1,
  "Nappe": 1,
  "la manche": 1,
  "58 MARIE-CLAIRE\n\nJe r\u00e9pondit :\n\n\u2014": 1,
  "De": 1,
  "Communs": 1,
  "Arr\u00eate": 1,
  "Blanche": 1,
  "mesentaissiabandonn\u00e9e": 1,
  "Iis": 1,
  "Cheval Blanc": 1,
  "S": 1,
  "sai": 1,
  "Brioche": 1,
  "Dour": 1,
  "lune": 1,
  "Pau-": 1,
  "ILS": 1,
  "M.Alphonse": 1,
  "E A": 1,
  "88 MARIE-CLAIRE": 1,
  "nant": 1,
  "gr\u00e9miller": 1,
  "Les": 1,
  "Gu\u00e9 Perdu": 1,
  "Gu\u00e9\nPerdu": 1,
  "M": 1,
  "A\u00e8le": 1,
  "lingerie": 1,
  "LA\n\nP": 1,
  "un\u00e9e": 1,
  "Deslois": 1,
  "champ de l\u00e9": 1,
  "Sautons": 1,
  "l\u2019Orphelinat": 1,
  "Bel-\u0152": 1,
  "Bel-\u0152il": 1,
  "Bel-\u0152\u00ef\u00fcl": 1,
  "pareil": 1,
  "cambrai": 1,
  "I": 1,
  "ch\u00e2teau du Gu\u00e9 Perdu": 1,
  "\u00ca": 1,
  "Bel-\u0152\u00efl": 1
}