{
  " Portobello": 11,
  " Edinburgh": 9,
  " Ireland": 5,
  " London": 4,
  "\n": 3,
  " Dublin": 3,
  " Princes Street": 2,
  " Spain": 2,
  " England": 2,
  " Yorkshire": 2,
  " Kilmarnoek Abbey": 2,
  "Edinburgl": 2,
  "\nonee": 2,
  "\nvain": 2,
  " Leith": 2,
  " Seotland": 2,
  " Porto-\nbello": 2,
  "\nsehool": 2,
  " Shannon": 2,
  " Limc-\nriok": 2,
  "Portohello": 2,
  "Oxford": 2,
  " Holyrood\nHouse": 2,
  "'s": 2,
  "Beaujolie\nCastle": 2,
  " Granvilles": 2,
  " St\nJohn's Lodge": 2,
  "\nEDINBURGH": 1,
  " Scotland": 1,
  " Por-\ntobello": 1,
  " Queensferry": 1,
  "\nv": 1,
  "Miy hame": 1,
  " Saul": 1,
  " gallory": 1,
  " rcaeh": 1,
  " Granville": 1,
  " Doncaster": 1,
  " gny": 1,
  " Argyleshire": 1,
  " Mid-Lothian": 1,
  "\nGalloway": 1,
  " Cromarty": 1,
  " Caithness": 1,
  " lBeaujolie Castlo": 1,
  "\nYorkshire": 1,
  " orkshire": 1,
  " Shetland": 1,
  " ek Abbey": 1,
  " IKil-\nmarnock Abbey": 1,
  "\nlPortobollo": 1,
  " Melton": 1,
  " IKilmarnoek\nAbbey": 1,
  " Beaujolie Castle": 1,
  " St Omers": 1,
  " lilmarnoek Abbey": 1,
  "Edinburgh": 1,
  " Britain": 1,
  " Court": 1,
  " Edin-\nburgh": 1,
  " whatovor": 1,
  "ton": 1,
  " Iritain": 1,
  " pl": 1,
  " rgyleshire": 1,
  " Castle High-\n": 1,
  " Kelso": 1,
  "\nopern": 1,
  "un": 1,
  "\nehamber": 1,
  " lan": 1,
  "\nguagos": 1,
  "ntrance": 1,
  "\nhall": 1,
  "Heaven": 1,
  "\ncourt": 1,
  " soeiety": 1,
  "\nbrealkfast": 1,
  " Great Britain": 1,
  "\nbeaeh": 1,
  "\nfrm sehool": 1,
  " Lunatic Asylum": 1,
  " ehill of\nnany": 1,
  " Ox-\nford": 1,
  " Mre Ponfold": 1,
  " Israel": 1,
  " sueh": 1,
  " juve-\nnile": 1,
  " Dartmore House": 1,
  "in\nown": 1,
  "o": 1,
  " genoral": 1,
  " elub": 1,
  "as": 1,
  " seh": 1,
  " sehool": 1,
  " Dartmore IHouse": 1,
  "\nwhiech": 1,
  "Piershill Barracks": 1,
  "\nLeeds": 1,
  " Canada": 1,
  " lenst": 1,
  "Paris": 1,
  " Scubeach\nottage": 1,
  " mo-\nmont": 1,
  " Piershill": 1,
  " Vauxhall": 1,
  " Seabeach\nCottage": 1,
  " gar": 1,
  "den": 1,
  " Sizr Ar-\nthur's": 1,
  " Rosemount\nVilla": 1,
  "\n'Aruh": 1,
  " t": 1,
  " Duhlin": 1,
  "\nIroland": 1,
  " Limeriek": 1,
  "Erin": 1,
  " Erin": 1,
  " win": 1,
  "\nlow": 1,
  " respigny": 1,
  " losemount Villa": 1,
  "aven": 1,
  "iety": 1,
  " Pon-\ntobello": 1,
  " Fife": 1,
  " Fiile": 1,
  " ohapel": 1,
  "ERN FLIHIA": 1,
  "ION": 1,
  " prineiple": 1,
  "\nyo": 1,
  " Doc": 1,
  "\nConstantinople": 1,
  " Holyrood": 1,
  "\nsanetuary": 1,
  "sanet": 1,
  " St John's Lodge": 1,
  " Holyrood House": 1,
  " Dartmoro Housel": 1,
  "\nbay": 1,
  " Mlelton": 1,
  " Australia": 1,
  "West Indies": 1,
  " el-\ngrave Square": 1,
  "-\n": 1,
  "\ncou": 1,
  "ont": 1,
  " Tower-\ncliffes": 1,
  " publie conel": 1,
  " Harrowgate": 1,
  " Mn\nGranville": 1,
  "Harrowgate": 1,
  " se": 1,
  "England": 1,
  " Ii": 1,
  " Iilmarnoek Abbey": 1,
  " Beaujolie": 1,
  " Moudoir": 1,
  "\nHighland": 1,
  " Bridge of Sighs": 1,
  " York-\nshirel Sueh": 1,
  " Iast": 1,
  " ch": 1,
  " daisiod\n": 1,
  " Arthur Seat": 1,
  " sanc-\ntuary": 1,
  " Skye": 1
}