{
  "Rosanette": 71,
  "Paris": 47,
  "I": 43,
  "A": 30,
  "Fr6deric": 28,
  "Nogent": 22,
  "MI": 21,
  "Vatnaz": 19,
  "el": 13,
  "Senecal": 13,
  "Dambreuse": 11,
  "Fred6ric": 10,
  "Est": 9,
  "Pellerin": 9,
  "clle": 9,
  "Dussardier": 9,
  "nice": 9,
  "France": 8,
  "Chartres": 8,
  "Mlais": 7,
  "Tuileries": 7,
  "E": 7,
  "Bourse": 7,
  "cn": 7,
  "Troyes": 6,
  "Deslau-": 6,
  "Venise": 6,
  "jura": 6,
  "Ca": 6,
  "Etat": 5,
  "Champagne": 5,
  "Italie": 5,
  "ct": 5,
  "Marechale": 5,
  "Creil": 5,
  "llosanette": 5,
  "Nonancourt": 5,
  "toul": 4,
  "boulevard Montmartre": 4,
  "Sens": 4,
  "Roque": 4,
  "ILes": 4,
  "Pantheon": 4,
  "Luxembourg": 4,
  "Francais": 4,
  "Fr4deric": 4,
  "Allemagne": 4,
  "ouil": 4,
  "O": 4,
  "Capitale": 4,
  "h0tel": 4,
  "Anglais": 4,
  "Iille": 4,
  "gargon": 4,
  "Marchale": 4,
  "rue Paradis": 4,
  "Bordelaise": 4,
  "Champ de Mars": 4,
  "Rosa-": 4,
  "rue Tronchet": 4,
  "Republique": 4,
  "Ccile": 4,
  "Cite": 3,
  "Suisse": 3,
  "breuse": 3,
  "Fortelle": 3,
  "Amerique": 3,
  "Ln": 3,
  "Arnou": 3,
  "de France": 3,
  "rue de Fleurus": 3,
  "Gaillon": 3,
  "Bordeaux": 3,
  "Tiens": 3,
  "Palais": 3,
  "Chine": 3,
  "donc?n": 3,
  "bois de Boulogne": 3,
  "pre Roque": 3,
  "ger": 3,
  "ple": 3,
  "faisaicnt": 3,
  "Gymnase": 3,
  "Pologne": 3,
  "Chinois": 3,
  "dine": 3,
  "Marcchale": 3,
  "quai Voltaire": 3,
  "Sncal": 3,
  "la France": 3,
  "Belleville": 3,
  "lille": 3,
  "lEst": 3,
  "de-": 3,
  "Soitl": 3,
  "Lyon": 3,
  "Progrs": 3,
  "Seine": 3,
  "llle": 3,
  "Fontainebleau": 3,
  "Fumichon": 3,
  "Turque": 3,
  "Vil": 2,
  "Saint-Louis": 2,
  "chine": 2,
  "la Seine": 2,
  "Dej": 2,
  "Russie": 2,
  "Montereau": 2,
  "meltre": 2,
  "Corbeil": 2,
  "Villenauxe": 2,
  "la Capitale": 2,
  "Nogentais": 2,
  "rue d'Anjou": 2,
  "sommc": 2,
  "rue Montmartre": 2,
  "bless6": 2,
  "Derrire": 2,
  "Cisy": 2,
  "Iy": 2,
  "P": 2,
  "rue de Clery": 2,
  "quai Napoleon": 2,
  "comnme": 2,
  "Montmartre": 2,
  "Sij'": 2,
  "Bordelais": 2,
  "rue de Choiseul": 2,
  "rue Saint-Jacques": 2,
  "Allons": 2,
  "Naples": 2,
  "G": 2,
  "poele": 2,
  "souflle": 2,
  "Porte-Saint-Martin": 2,
  "Saint-Cloud": 2,
  "Pour-": 2,
  "c0te de Paris": 2,
  "Londres": 2,
  "Melun": 2,
  "gre": 2,
  "barribre": 2,
  "La Seine": 2,
  "Louvre": 2,
  "Poisson-": 2,
  "Regimbart": 2,
  "luil": 2,
  "Turcs": 2,
  "ngres": 2,
  "Freleric": 2,
  "Mondor": 2,
  "llavre": 2,
  "Montpensier": 2,
  "monsicur": 2,
  "Suissesse": 2,
  "Turc": 2,
  "volupte": 2,
  "repondre": 2,
  "Postillon": 2,
  "Mare-": 2,
  "bannibres": 2,
  "lEurope": 2,
  "Nantes": 2,
  "Il1": 2,
  "Vutnaz": 2,
  "Fr6leric": 2,
  "dinant": 2,
  "camelias": 2,
  "Providence": 2,
  "Angleterre": 2,
  "cheminee": 2,
  "vtre": 2,
  "martre": 2,
  "leil": 2,
  "Arc": 2,
  "boheme": 2,
  "Art": 2,
  "Palais-Royal": 2,
  "Saintonge": 2,
  "rue Saint-Denis": 2,
  "ranquille": 2,
  "Madrid": 2,
  "Frleric": 2,
  "oque": 2,
  "pltre": 2,
  "refleclir": 2,
  "Italiens": 2,
  "hommcs": 2,
  "Vivienne": 2,
  "aris": 2,
  "Vincennes": 2,
  "Saint-Antoine": 2,
  "Sen6cal": 2,
  "J": 2,
  "ttete": 2,
  "mele": 2,
  "candelabres": 2,
  "rue Rumfort": 2,
  "Iin": 2,
  "porte Saint-Martin": 2,
  "Mareclale": 2,
  "Pa-": 2,
  "pcuple": 2,
  "IIL": 2,
  "Aube": 2,
  "Panthon": 2,
  "Aprs": 2,
  "ler": 2,
  "Amiens": 2,
  "Grmonville": 2,
  "Languedoc": 2,
  "tSaint-Bernard": 1,
  "v-": 1,
  "Notre-Dame": 1,
  "Nogent-sur-Seine": 1,
  "roulte": 1,
  "la couronnaicnt": 1,
  "Eles": 1,
  "geraniums": 1,
  "cmpgne": 1,
  "voy1ge": 1,
  "chile": 1,
  "lisire": 1,
  "crdole": 1,
  "cntra": 1,
  "ablmes": 1,
  "rayonnemcnt": 1,
  "Commecnt": 1,
  "Surville": 1,
  "longca": 1,
  "corlerie": 1,
  "Bray": 1,
  "Ablon": 1,
  "Chitillon": 1,
  "A Bray": 1,
  "vilure": 1,
  "Armes,1": 1,
  "cheminde": 1,
  "jurisconsulle": 1,
  "ii": 1,
  "sulon": 1,
  "lticn": 1,
  "Cygne de la Cvroiz": 1,
  "qand": 1,
  "collbge": 1,
  "lhuissier": 1,
  "Troisibme": 1,
  "Maul-": 1,
  "rue des Irois-llois": 1,
  "gnealogic\ndu Christ": 1,
  "porlail": 1,
  "Comines": 1,
  "dortoir,18\nL' i": 1,
  "musique20\nL' i": 1,
  "Rvolution frangaise": 1,
  "Iamour": 1,
  "renoncc": 1,
  "Frederic.2": 1,
  "Ft": 1,
  "Iu reussiras": 1,
  "currefour de 1Htel-\nDieu": 1,
  "rue Coq-Ileron": 1,
  "Ambreuse": 1,
  "l'Aube": 1,
  "N1ALE": 1,
  "dressce": 1,
  "lindre": 1,
  "Deloin": 1,
  "accusuicnt": 1,
  "vasists": 1,
  "cetle": 1,
  "tonnee": 1,
  "avangca": 1,
  "Tond": 1,
  "rue Saint-Hyacinthe": 1,
  "Loure": 1,
  "Milles": 1,
  "Las": 1,
  "tre srieux": 1,
  "cafe": 1,
  "Sainte-\nChapelle": 1,
  "Notre-Dume": 1,
  "NTI.E": 1,
  "louze": 1,
  "lchira": 1,
  "Champs-": 1,
  "femmcs": 1,
  "chet": 1,
  "llarpe": 1,
  "quinquet": 1,
  "lumides": 1,
  "Collige de France": 1,
  "fnee": 1,
  "iaon mediocre": 1,
  "prilt": 1,
  "quai Napolon": 1,
  "Saint-Jacques": 1,
  "cafds": 1,
  "rue Souflot": 1,
  "recensemcnt": 1,
  "amenaicnt": 1,
  "Fderic": 1,
  "mutineriec": 1,
  "Jcu-": 1,
  "comprilt": 1,
  "melre": 1,
  "svit": 1,
  "Guizol": 1,
  "retirez-vousl": 1,
  "etoupes": 1,
  "Arrtte": 1,
  "rue\nSaint-Jacques": 1,
  "SENTI E NTALE": 1,
  "Dussar-": 1,
  "platre": 1,
  ".Malgre": 1,
  "connaissez?n\n": 1,
  "Bobino": 1,
  "Frangcuais": 1,
  "Vourdat": 1,
  "cun": 1,
  "Apollonie": 1,
  "Burricu": 1,
  "boulevrd": 1,
  "lns": 1,
  ".Puis": 1,
  "cleminee": 1,
  "Gouverne-": 1,
  "Californie": 1,
  "Belgique": 1,
  "lInstitut": 1,
  "Frddric": 1,
  "A6": 1,
  "piece": 1,
  "Poissonnibre": 1,
  "ceudie e Ioe": 1,
  "Winc-\nkelmann": 1,
  "Quanl": 1,
  "honnete": 1,
  "National": 1,
  "Notre-Dame-des-Victoires": 1,
  "Bretagne": 1,
  "l'Italie": 1,
  "hison": 1,
  "rpondre": 1,
  "discutaitla": 1,
  "Geneve": 1,
  "lante": 1,
  "L:-": 1,
  "joubliais": 1,
  "decoree i": 1,
  "lainc": 1,
  "Lovarias": 1,
  "Boheme": 1,
  "Q'": 1,
  "Iien": 1,
  "Mlichiel": 1,
  "Bassolier": 1,
  "L'Olympe": 1,
  "soltises": 1,
  "EU": 1,
  "gere": 1,
  "ceoilfure": 1,
  "eprouva": 1,
  "sV": 1,
  "Elait": 1,
  "Les reverberes": 1,
  "dela": 1,
  "Pont-Neuf": 1,
  "dcclara": 1,
  "couleuu": 1,
  "Comimnent": 1,
  "Vnus": 1,
  "Montrez": 1,
  "Irangcaise": 1,
  "femmle": 1,
  "grace": 1,
  "semcnt": 1,
  "Dambreuses": 1,
  "Constantinople": 1,
  "Art industiel": 1,
  "scuris": 1,
  "yeux,68": 1,
  "Iegimbart": 1,
  "NTIIENTA ILE": 1,
  "senleur": 1,
  "mpris": 1,
  "alorsl": 1,
  "se-\nmaine": 1,
  "mpe": 1,
  "la thiire": 1,
  "Gouver-": 1,
  "Pritchurl": 1,
  "trulles": 1,
  "Anda-": 1,
  "brune": 1,
  "toujoursl": 1,
  "Sorbonne": 1,
  "kRhin": 1,
  "lologne": 1,
  "curo": 1,
  "Enlin": 1,
  "legimburt": 1,
  "Brie": 1,
  "Balandard": 1,
  "avou": 1,
  "ommne": 1,
  "premiire": 1,
  "sicnnes": 1,
  "L'E": 1,
  "verezl": 1,
  "lussonnet": 1,
  "Ellel": 1,
  "ceda": 1,
  "bDonc": 1,
  "liacre": 1,
  "defaillir": 1,
  "sor aeil": 1,
  "Ormes": 1,
  "port le Montereau": 1,
  "tour Saint-": 1,
  "Sait-tGervais": 1,
  "Saint-Paul": 1,
  "colonne de Juillet": 1,
  "etoile dor": 1,
  "dome des Tuileries": 1,
  "cte-l": 1,
  "collges": 1,
  "Avrt": 1,
  "attenlri": 1,
  "prcmire": 1,
  "Bourgogne": 1,
  "Saumon": 1,
  "laccompagner": 1,
  "rue de Richelieu": 1,
  "Les prostituees": 1,
  "Jardin des Plantes": 1,
  "uelquefois": 1,
  "Flandres": 1,
  "s6-": 1,
  "abaltre": 1,
  "Champs-lilysees": 1,
  "plilre": 1,
  "Ibes": 1,
  "allees": 1,
  "l'Amerique": 1,
  "nankin": 1,
  "L'EDUCATI0N SENTIMENTALE": 1,
  "cancan": 1,
  "Tache": 1,
  "Attendrais": 1,
  "SE NT1MENTALE": 1,
  "le Iyve": 1,
  "rs": 1,
  "manche": 1,
  "Censure": 1,
  "lesL' EDUCATI0N SENTIMENTALE": 1,
  "Bengale": 1,
  "poudrc": 1,
  "le France": 1,
  "bleme": 1,
  "blama": 1,
  "rue de Rivoli": 1,
  "Chatelet": 1,
  "quai Napo-\nleon": 1,
  "la9": 1,
  "lumibre": 1,
  "pont de la Concorde": 1,
  "lune": 1,
  "vic": 1,
  "essya": 1,
  "lonzelle": 1,
  "Andalouse": 1,
  "periphrases": 1,
  "dcore": 1,
  "rue de Cloiseul": 1,
  "convenul lPardon": 1,
  "Trop": 1,
  "ioius": 1,
  "sEN": 1,
  "cenltuple": 1,
  "Irequcntation": 1,
  "lombreclle": 1,
  "celal": 1,
  "la soiree": 1,
  "lebarquait  Saint-Cloud": 1,
  "Sombaz": 1,
  "Ecosse": 1,
  "Boulogne": 1,
  "Neuilly": 1,
  "Svres": 1,
  "Meudon": 1,
  "cerains": 1,
  "aisers": 1,
  "Auteuil": 1,
  "chosc": 1,
  "serin-L'": 1,
  "Garde-Meuble": 1,
  "III": 1,
  "Cumarilla": 1,
  "asec": 1,
  "renouveles": 1,
  "Presles": 1,
  "menl": 1,
  "tres;-": 1,
  "L'EDUcATI0N": 1,
  "dependaient": 1,
  "Ilfautavertir": 1,
  "regardit": 1,
  "Fouvens": 1,
  "Catherine": 1,
  "Lorraine": 1,
  "llisbeth-Olympe-Louise HRoque": 1,
  "sevre": 1,
  "tourmentt": 1,
  "bitns": 1,
  "ige": 1,
  "tour de Montereau": 1,
  "rsignee": 1,
  "L'apres-midi": 1,
  "Malemoiselle": 1,
  "etune": 1,
  "chuclola": 1,
  "Cautherine": 1,
  "IM": 1,
  "wP": 1,
  "tioi\nFe": 1,
  ".::": 1,
  "isiitgaioic": 1,
  ".,'.-": 1,
  "s-": 1,
  "A-": 1,
  "PAITIDQuant": 1,
  "l1l'": 1,
  "c0te de Sourlun": 1,
  "limoniers": 1,
  "pont de Charenton": 1,
  "terre": 1,
  "bDe": 1,
  "ena": 1,
  "heuf": 1,
  "bicoue": 1,
  "pllre": 1,
  "hrume": 1,
  "tombereitx": 1,
  "Jrdin": 1,
  "Iouleuses": 1,
  "quai Saint-Bernard": 1,
  "la Tournelle": 1,
  "quai Montebello": 1,
  "quai\nNapoleon": 1,
  "le Pont-Neuf": 1,
  "Saint-Honor6": 1,
  "Bouloi": 1,
  "rue\nCoq-Heron": 1,
  "Mlontmartre": 1,
  "cheri": 1,
  "rue de Choisceul": 1,
  "ArnouX": 1,
  "rue le Fleurus": 1,
  "rue Notre-\nDame-des-Victoires": 1,
  "sr": 1,
  "enais": 1,
  "gurgotier": 1,
  "Sainte-Genevieve": 1,
  "Siele": 1,
  "levenu": 1,
  "rue\nSaint-Mlartin": 1,
  "Iond": 1,
  "Oi1": 1,
  "rue Paradis-Poissonnibre": 1,
  "Citoyen etonne": 1,
  "Alieu": 1,
  "sonnelte": 1,
  "sa lille": 1,
  "Frede-": 1,
  "tltc": 1,
  "Renaissance": 1,
  "caufe Anglais": 1,
  "sujcet": 1,
  "Gaulois": 1,
  "Irlandais": 1,
  "Vazeille": 1,
  "Savigny": 1,
  "Troplong": 1,
  "lerahles": 1,
  "Parlotte": 1,
  "St": 1,
  "llanelle rouge": 1,
  "Vlour": 1,
  "societc": 1,
  "genie peut-etre": 1,
  "accoudes": 1,
  "Iense": 1,
  "Barthlemy": 1,
  "Colosse": 1,
  "Pomnadre": 1,
  "Chevcet": 1,
  "Laval": 1,
  "marmiton": 1,
  "joic": 1,
  "Mrnoux": 1,
  "Gare": 1,
  "yaltagans": 1,
  "soie gris-pele": 1,
  "i": 1,
  "1Unit": 1,
  "lonc": 1,
  "cinabe": 1,
  "tranquille": 1,
  "soleillant": 1,
  "IEt": 1,
  "Plazot": 1,
  "cevat": 1,
  "monl1e": 1,
  "lrire": 1,
  "MIis": 1,
  "mnains": 1,
  "Longjumeau": 1,
  "Dbardeuse": 1,
  "Dantc": 1,
  "pt-dcsstts": 1,
  "cueil de litterature": 1,
  "Etle": 1,
  "Fr4lerie": 1,
  "scs ycux": 1,
  "i Iosanctte": 1,
  "Sphinx": 1,
  "Benedicite": 1,
  "I.f": 1,
  "Celutal": 1,
  "charmnantel": 1,
  "piquees": 1,
  "Dbarleuse": 1,
  "volire": 1,
  "ldont": 1,
  "bour de basque": 1,
  "Debardeuse": 1,
  "orang-outang": 1,
  "Iois": 1,
  "llosnette": 1,
  "attablee": 1,
  "liacres": 1,
  "Sauvagcsse": 1,
  "ta soiree": 1,
  "Poissarde": 1,
  "Debar-": 1,
  "Sauvugesse": 1,
  "Atls": 1,
  "Dictionaires": 1,
  "Huvre": 1,
  "Espagnolet": 1,
  "lloquence": 1,
  "labbe\nCeur": 1,
  "domestiqucs": 1,
  "Mont-": 1,
  "campatgne": 1,
  "decousue": 1,
  "congediee": 1,
  "Flanque": 1,
  "rue Joubert": 1,
  "Temple": 1,
  "Delmar.16": 1,
  "Montagne": 1,
  "MIade-": 1,
  "Marthene": 1,
  "Saint-Cloul": 1,
  "Havre": 1,
  "kEtat": 1,
  "Ili": 1,
  "nais": 1,
  "coipagnie": 1,
  "fastilieuse": 1,
  "bcsogne": 1,
  "linie": 1,
  "Iably": 1,
  "Buzancais": 1,
  "cafe170": 1,
  "Dagneaux": 1,
  "Saint-Denis": 1,
  "Sene--": 1,
  "Chateau": 1,
  "Saint-": 1,
  "chicards": 1,
  "epaules": 1,
  "atalogue": 1,
  "Allemand": 1,
  "Permettezl": 1,
  "Salons": 1,
  "Vatican": 1,
  "delices": 1,
  "Saint-Mlarceau": 1,
  "Suaint-Barthelemy": 1,
  "proletaire": 1,
  "kaolin de Bretagne": 1,
  "haissa": 1,
  "Mloulin-Rouge": 1,
  "ciseax": 1,
  "c0te-l": 1,
  "compgnie": 1,
  "kosanelte": 1,
  "metlre": 1,
  "jce": 1,
  "bor augure": 1,
  "resolut": 1,
  "Mlurechale": 1,
  "chucholer": 1,
  "burnousl": 1,
  "plutt": 1,
  "orfevrerie": 1,
  "Lnissez": 1,
  "deesses": 1,
  "Iixa": 1,
  "rue du Bac": 1,
  "pont Royal": 1,
  "Notrc-Dame": 1,
  "Ptisserie": 1,
  "rue de la Paix": 1,
  "Fllo": 1,
  "bliotheque": 1,
  "SENTIMENTA": 1,
  "Dambreuselon": 1,
  "petitl Soyez": 1,
  "Seigneurl": 1,
  "ln190": 1,
  "lechafaud": 1,
  "la somme": 1,
  "Cher": 1,
  "Osage": 1,
  "teau dore": 1,
  "T10N": 1,
  "Partout": 1,
  "jasmin": 1,
  "le bulfet": 1,
  "Republiquel": 1,
  "Pressel": 1,
  "au-\nres": 1,
  "humaine196\n": 1,
  "Anglaises": 1,
  "keepsake": 1,
  "Italienne": 1,
  "Vesuve": 1,
  "Normandes": 1,
  "lentelles": 1,
  "le Molire": 1,
  "au-\ntre porte": 1,
  "tristel": 1,
  "veloursl": 1,
  "Flacourt": 1,
  "Bertinaux": 1,
  "Saint-Valery": 1,
  "bete": 1,
  "geniel": 1,
  "Persan": 1,
  "rue de Laval": 1,
  "Lesurques": 1,
  "Ah1": 1,
  "carcel": 1,
  "gote": 1,
  "Voil": 1,
  "Rosanettel": 1,
  "rs do": 1,
  "Barnais": 1,
  "ngoue": 1,
  "cruinte de deplaire": 1,
  "l'Espagne": 1,
  "rue Sainte-Anne": 1,
  "jaais": 1,
  "saulter": 1,
  "c0u": 1,
  "Salamanque": 1,
  "la v0tre": 1,
  "T,'": 1,
  "rue des Trois-Marics": 1,
  "la Pologne": 1,
  "licu": 1,
  "Au-": 1,
  "Alpes": 1,
  "Ita-": 1,
  "gouvernementl": 1,
  "au-\ntre": 1,
  "Ilfallait": 1,
  "Comedie-Francaise": 1,
  "croisales": 1,
  "Celles": 1,
  "MP Beau-\nminet": 1,
  "rue Sint-Anne": 1,
  "mlavancer": 1,
  "neroy": 1,
  "r6pte": 1,
  "Vaudeville": 1,
  "genaier": 1,
  "E.i.-": 1,
  "la Made-": 1,
  "rue\nIauteville": 1,
  "rue de Chabrol": 1,
  "Ga-": 1,
  "Commerce": 1,
  "boulevard Saint-Denis": 1,
  "c:::::::ti": 1,
  "tetel": 1,
  "rue de Breda": 1,
  "navre": 1,
  "seuil de la lorette": 1,
  "pele-mele": 1,
  "d'Espagne": 1,
  "aeo\n-  ": 1,
  "cte": 1,
  "Anglaise": 1,
  "Institut": 1,
  "le Puys": 1,
  "Limportance": 1,
  "AVez": 1,
  "pont de la Boucherie": 1,
  "Montataire": 1,
  "barribre du236": 1,
  "d6flle": 1,
  "FEt": 1,
  "nUCATI0N": 1,
  "liecu-commun": 1,
  "musee": 1,
  "decoraitles": 1,
  "faenza": 1,
  "gcs": 1,
  "At": 1,
  "Ile Marthe": 1,
  "tamise": 1,
  "patouillards": 1,
  "IIl": 1,
  "mathemalique": 1,
  "soufIle": 1,
  "ypes": 1,
  "auhasard": 1,
  "Pur": 1,
  "Frderic.28": 1,
  "E UcATI0N sENTIMENTAILE": 1,
  "place de la": 1,
  "Billy": 1,
  "kRosannette": 1,
  "Liban": 1,
  "Trocadro": 1,
  "Champ\ne MIars": 1,
  "lloi": 1,
  "Filly": 1,
  "Tibi": 1,
  "Clubstick": 1,
  "Chantilly": 1,
  "L'EDUCATI0N sSENTIMENTALE": 1,
  "Hippodrome": 1,
  "lernier depart": 1,
  "Amcricains": 1,
  "Bachelu": 1,
  "L.i": 1,
  "losc": 1,
  "Ohe l": 1,
  "caf Anglais": 1,
  "Champs-Elysees": 1,
  "wurt": 1,
  "laissu": 1,
  "tte": 1,
  "etail": 1,
  "Garde-Meubles": 1,
  "Moulevard": 1,
  "Buins-Chinois": 1,
  "U": 1,
  "mune": 1,
  "Collge de France": 1,
  "Richelicu": 1,
  "Chambord": 1,
  "ourgogne": 1,
  "Aure": 1,
  "teuil": 1,
  "ples": 1,
  "Flabart": 1,
  "Canonniers": 1,
  "Gericault": 1,
  "lumire": 1,
  "tetre": 1,
  "ga": 1,
  "Lextravagance": 1,
  "revolta": 1,
  "permettezl": 1,
  "Samedi": 1,
  "Champ de Iars": 1,
  "suis sr": 1,
  "mur arrtta": 1,
  "degot": 1,
  "du Havre": 1,
  "mill": 1,
  "E\ntat": 1,
  "recut": 1,
  "Belle-": 1,
  "hypothques": 1,
  "quoi7": 1,
  "Mai-": 1,
  "Irangaise": 1,
  "leins": 1,
  "Unlustre": 1,
  "Aulnays": 1,
  "Capital": 1,
  "Iysteres": 1,
  "L'EpUCATI0N SENTIMENTALE": 1,
  "EDUCATIoN": 1,
  "ecluir": 1,
  "terre les debris": 1,
  "Precepteur": 1,
  "YOuS": 1,
  "virilite": 1,
  "ttetc": 1,
  "rclama": 1,
  "La Fougre": 1,
  "Y es-tu": 1,
  "brav\ngarcon lcha immdiatemcnt": 1,
  "curtel": 1,
  "quai d'Orsay": 1,
  "procbs-ver-\nul": 1,
  "pistolelt": 1,
  "on276": 1,
  "ILin": 1,
  "VWicomte": 1,
  "Irayeur": 1,
  "bois de Bologne": 1,
  "madras": 1,
  "Bagatelle": 1,
  "egalemen": 1,
  "basan": 1,
  "Fredecic": 1,
  "Monsiecur": 1,
  "Croyez": 1,
  "Ir": 1,
  "branchesl": 1,
  "lRegimbart": 1,
  "Cmu": 1,
  "Barante": 1,
  "Givondis": 1,
  "vee h Paris": 1,
  "Mont-\nmartre": 1,
  "Repnblique": 1,
  "Dussarlier": 1,
  "rue Transnonain": 1,
  "solduts": 1,
  "Toutle": 1,
  "Mont-Saint-Michel": 1,
  "lescalier": 1,
  "Miserables": 1,
  "Nord": 1,
  "MIme Dam": 1,
  "Annuaie": 1,
  "Gotha": 1,
  "Saint-Franois": 1,
  "auteuil": 1,
  "Empire cree": 1,
  "tete": 1,
  "lche": 1,
  "hoiseric": 1,
  "notre7\n-  Lui": 1,
  "tunc": 1,
  "Iiciance de Napolon": 1,
  "carbonaro": 1,
  "tcha": 1,
  "Orlans": 1,
  "ahus": 1,
  "alors?n\n-  ": 1,
  "lbitit": 1,
  "du Nord": 1,
  "Heudras": 1,
  "Chambrion": 1,
  "pre Ro-": 1,
  "Parisien": 1,
  "ILouise": 1,
  "Lavernade": 1,
  "I'Etrigny": 1,
  "Villeneuve-l'Archevque": 1,
  "Iauteuil": 1,
  "resume": 1,
  "Alrs": 1,
  "gateaux": 1,
  "chur": 1,
  "lacloche": 1,
  "E nucATI0N SENTIMIENTAILE": 1,
  "Autre-": 1,
  "lile": 1,
  "vOulez-Vus": 1,
  "xt'": 1,
  "Niagara": 1,
  "El": 1,
  "Iu": 1,
  "mari?n": 1,
  "EncATI0N sENTIMIENTAIL E": 1,
  "lh-bas": 1,
  "boulevard sen": 1,
  "Quclle": 1,
  "Naturel": 1,
  "Russe": 1,
  "carcel posee sur \ngueridon": 1,
  "Certainementl": 1,
  "Franc": 1,
  "comprena": 1,
  "rue Grange-Batelire": 1,
  "EDUCATI0N SENTI MENTALE": 1,
  "Bellevue": 1,
  "L": 1,
  "clloc": 1,
  "retoutr": 1,
  "EnDUcATI0N": 1,
  "pau": 1,
  "gorge-de-pigeon": 1,
  "Adieuln": 1,
  "nUCA": 1,
  "Ineuves": 1,
  "mdiocre": 1,
  "Mystres": 1,
  "Norvins": 1,
  "Pie-": 1,
  "Toscane": 1,
  "Lille": 1,
  "ligne du Norl": 1,
  "uatre-vingts": 1,
  "Regence": 1,
  "Hussonne": 1,
  "caressan": 1,
  "Ecoutez-": 1,
  "chter": 1,
  "nille": 1,
  "puncl": 1,
  "quai Napo\nleon": 1,
  "Aussit0t Freleric": 1,
  "lanoblesse": 1,
  "llsou-": 1,
  "Lheure": 1,
  "pre l'ecrivit": 1,
  "ployes": 1,
  "c:-": 1,
  "macons": 1,
  "sonamour": 1,
  "Palais-\nRoyal": 1,
  "college": 1,
  "Provi-": 1,
  "pos-L' fED": 1,
  "Bientot": 1,
  "Palerme": 1,
  "Nlle": 1,
  "L'EDUcATI0N sENTIMENTALE": 1,
  "sicnne": 1,
  "rue de la Ferme ? \n": 1,
  "Appar": 1,
  "anca": 1,
  "Mlinistk": 1,
  "Pou": 1,
  "rue de l'Arcade": 1,
  "cervclle": 1,
  "rue de la Ferme et de la rue Tronchet": 1,
  "voyge": 1,
  "cpagne": 1,
  "perail": 1,
  "succedrcnt": 1,
  "lourdes": 1,
  "elfraya": 1,
  "Savoyard": 1,
  "toilon": 1,
  "Trois-\nrbres-Provencaux": 1,
  "rue Caumartin": 1,
  "htel": 1,
  "reveillee": 1,
  "ARTIELe": 1,
  "Champs-llyses": 1,
  "Chateau-": 1,
  "Saint-Thomas": 1,
  "Fromanteau": 1,
  "rue de Valois": 1,
  "A c0te": 1,
  "EDUCAT10N sENTIMENTALE": 1,
  "serpillire": 1,
  "ebranlie": 1,
  "ctzx": 1,
  "Pa": 1,
  "place du\nCarrousel": 1,
  "d0me du Louvre": 1,
  "Mr6chaux": 1,
  "Ls": 1,
  ".;;te": 1,
  "Cancane": 1,
  "la Bastille": 1,
  "prostituees": 1,
  "dlire": 1,
  "rue Fromanteau": 1,
  "jardin des Tuileries": 1,
  "a357\nLattention de Fred6ric": 1,
  "hire": 1,
  "cntr": 1,
  "ux Tuileries": 1,
  "brandissa": 1,
  "partou": 1,
  "EcATI0N": 1,
  "ILelru-llollin": 1,
  "Icoles": 1,
  "Rpublique": 1,
  "Magis-": 1,
  "Mlurchux": 1,
  "Changrnier": 1,
  "Champ de\nIars": 1,
  "Murcchale": 1,
  "consciller": 1,
  "pont d'Arcole": 1,
  "Esthtique": 1,
  "bientl": 1,
  "Eure": 1,
  "vicille": 1,
  "Rhin": 1,
  "Iichtre": 1,
  "La France": 1,
  "Somme": 1,
  "ome": 1,
  "Vienne": 1,
  "Berlin": 1,
  "Autrichiens": 1,
  "rentrentchez": 1,
  "vengence;-": 1,
  "Vntnaz": 1,
  "Francaise": 1,
  "juIry": 1,
  "Pelle-": 1,
  "lquelle": 1,
  "Onse": 1,
  "tSaint-Jacques": 1,
  "premiertail": 1,
  "lille Com-\nain": 1,
  "marquede": 1,
  "vrole": 1,
  "accrochs": 1,
  "aupires": 1,
  "Prado": 1,
  "P.s": 1,
  "Chapeau": 1,
  "Jean-acques Langreneux": 1,
  "rue Dauphine": 1,
  "Linsuccs": 1,
  "crpu": 1,
  "ain": 1,
  "catechumnes": 1,
  "ulcools": 1,
  "tempete": 1,
  "ecarta": 1,
  "EnUc": 1,
  "Conservons-les": 1,
  "Quelquun": 1,
  "Dus-": 1,
  "sarlier": 1,
  "pacto fundamental de las libertades espanolas": 1,
  "Sortezl": 1,
  "Ibcrien": 1,
  "milica": 1,
  "l2aris": 1,
  "llamaria yo el pri-": 1,
  "Hlurons": 1,
  "L'EDUCATI0N": 1,
  "Essniens": 1,
  "Auvergne": 1,
  "yeu": 1,
  "Infin": 1,
  "lDonc": 1,
  "lelle": 1,
  "rue Drouot": 1,
  "de382": 1,
  "baissee": 1,
  "pasrecu": 1,
  "uis": 1,
  "Pvesse": 1,
  "gemit": 1,
  "cur": 1,
  "Carousel": 1,
  "tinie": 1,
  "Frelric": 1,
  "turge": 1,
  "Frcleric": 1,
  "ligne du Nord": 1,
  "cxcs": 1,
  "reparult": 1,
  "Mlarie": 1,
  "bnnissement des d'Orleans": 1,
  "SENTI": 1,
  "Bastille": 1,
  "Chitelet": 1,
  "porte Saint-Denis": 1,
  "ch-": 1,
  "Mriques": 1,
  "Cerfs": 1,
  "salle\ndes Gardes": 1,
  "Trone": 1,
  "lumire blanche": 1,
  "Ilesperides": 1,
  "sETIMIENTALE": 1,
  "coudoye": 1,
  "Pharamond": 1,
  "Aspremont": 1,
  "aeil": 1,
  "c0te de Chailly": 1,
  "Gorge-au-Loup": 1,
  "Iare-aux-Fces": 1,
  "Long-llocher": 1,
  "Marlotte": 1,
  "mollemnenl": 1,
  "formient": 1,
  "lissc": 1,
  "frines": 1,
  "brtles": 1,
  "plalcs": 1,
  "tahle": 1,
  "fenclre": 1,
  "la chine": 1,
  "lherbe": 1,
  "Freleric.d": 1,
  "UCcATI0N SENTIMENTAILE": 1,
  "Fre-": 1,
  "OuY.rd": 1,
  "bellel": 1,
  "Vicns": 1,
  "Imoi": 1,
  "A05": 1,
  "Bourbonnais": 1,
  "Marchd": 1,
  "dpartement voulaicnt continucr": 1,
  "Rosanetlte": 1,
  "mela": 1,
  "Arriv": 1,
  "barribre d'Italie": 1,
  "Canaille": 1,
  "boulevards des Gobelins": 1,
  "H-": 1,
  "rue Bellefond": 1,
  "Jardin des Plantes.ed": 1,
  "rue du Marcle-aux-\nhevaux": 1,
  "Jardin des llautes": 1,
  "llmbuit": 1,
  "licole polytechnique": 1,
  "rue Saint-Victor": 1,
  "NIl arrondissement": 1,
  "bivac": 1,
  "Negricr": 1,
  "dCcbarque  Boulogne": 1,
  "de Bourges": 1,
  "MI arrondissement": 1,
  "I00": 1,
  "levs": 1,
  "Carrousel": 1,
  "Honneur": 1,
  "Celte": 1,
  "rue Vivicnne": 1,
  "Allez": 1,
  "lRepublique": 1,
  "nommc": 1,
  "rejcla": 1,
  "Tui-": 1,
  "Ilot": 1,
  "rue Saint-Martin": 1,
  "gers": 1,
  "Chbre": 1,
  "MIise-": 1,
  "renoncant": 1,
  "monotone": 1,
  "Cisy?n": 1,
  "Ionl": 1,
  "Monsei-": 1,
  "deplorer": 1,
  "cclui de Lamoricire": 1,
  "Ilpublique": 1,
  ".'etre": 1,
  "Rque": 1,
  "Tournez": 1,
  "Roquel": 1,
  "maine": 1,
  "sangl": 1,
  "liiIrencc": 1,
  "glacee do surprisc": 1,
  "capelire": 1,
  "trs bas": 1,
  "reprenaicnt": 1,
  "circulezl": 1,
  "Louisefut": 1,
  "accouds": 1,
  "llosaneltte": 1,
  "Borde-": 1,
  "manquaicnt": 1,
  "commenccr": 1,
  "Jouflroy": 1,
  "I35": 1,
  "1Illustation": 1,
  "Cham": 1,
  "vienslo": 1,
  "Partezl partezl": 1,
  "arracla": 1,
  "Champ-de-Mars": 1,
  "gravemcnt": 1,
  "disunt": 1,
  "soutenuc": 1,
  "ctaicnt": 1,
  "Cepcndant": 1,
  "intertts": 1,
  "amusaitl": 1,
  "Balaruc": 1,
  "cssaya": 1,
  "Poitiers": 1,
  "Conslitulion": 1,
  "bcaucoup": 1,
  "cmpagnes": 1,
  "Gremonville": 1,
  "journce": 1,
  "Conservatoire": 1,
  "tibde": 1,
  "chillonnires": 1,
  "Etretat": 1,
  "Frisonne": 1,
  "emouvoir": 1,
  "ldternelle": 1,
  "Amourl": 1,
  "lultte": 1,
  "banquicr": 1,
  "Ec::::':-": 1,
  "Isle": 1,
  "compltc": 1,
  "Misericorde": 1,
  "Lillec": 1,
  "R": 1,
  "illusionsl": 1,
  "A52 L.'EDUCATI0N sENTIMENTALE": 1,
  "cblouie": 1,
  "peut-tetre": 1,
  "l.": 1,
  "si-": 1,
  "lindulgence": 1,
  "lironie": 1,
  "fentres": 1,
  "Irayante": 1,
  "dunger": 1,
  "lc -\nmedecin": 1,
  "taillel": 1,
  "A59": 1,
  "II60": 1,
  "gnol": 1,
  "Combien": 1,
  "Picardie": 1,
  "breviaire": 1,
  "Halles": 1,
  "remcnt": 1,
  "funbres": 1,
  "llI0tel-de-Ville": 1,
  "seucestochre do": 1,
  "clarte blanche": 1,
  "Pere-Lachaise": 1,
  "crepe": 1,
  "Presi-": 1,
  "steles": 1,
  "fosse de M. Dambreuse": 1,
  "Chambre des depules": 1,
  "Sane-et-\nLoire": 1,
  "La terre": 1,
  "bonhcur": 1,
  "rue de Marbueuf": 1,
  "Maternite": 1,
  "Iierte": 1,
  "et6e": 1,
  "derangements": 1,
  "I72": 1,
  "Andilly": 1,
  "Marechle": 1,
  "l'Empire": 1,
  "Orleans": 1,
  "Versailles": 1,
  "Autorit": 1,
  "ancienne176": 1,
  "Saint-Germain": 1,
  "Mattre": 1,
  "ticicns": 1,
  "Frederie": 1,
  "Dicu": 1,
  "pcrdue": 1,
  "place de la Bastille": 1,
  "gie": 1,
  ".l": 1,
  "Qui?n": 1,
  "Arn0ux": 1,
  "forlune": 1,
  "ecnseigne": 1,
  "cinabrc ct d'azur": 1,
  "chalel": 1,
  "beuf": 1,
  "Saint-Pre": 1,
  "lexislence": 1,
  "EnDUCATI0N": 1,
  "lou6": 1,
  "Baslin": 1,
  "Dsualtevnisation": 1,
  "complicel": 1,
  "Vatnazl": 1,
  "incATI0N SENTIMENTALE": 1,
  "baionnetles": 1,
  "moyenl": 1,
  "osanette": 1,
  "Senc-\ncal": 1,
  "blessee": 1,
  "kFredric": 1,
  "laudicnce": 1,
  "lavie": 1,
  "Hosnette": 1,
  "ressemblancel A": 1,
  "Regardez": 1,
  "rue Jacob": 1,
  "au Havre": 1,
  "La somme": 1,
  "logcail": 1,
  "lescalicr": 1,
  "Mlonsieur": 1,
  "rue de l'Empereur": 1,
  "gare du Havre": 1,
  "toyen": 1,
  "cte de Paris": 1,
  "chagrin?n\n": 1,
  "avaitrecu": 1,
  "lome-li": 1,
  "Chine ct du\nJapon": 1,
  "EncATI0N sSENTIMENTALE": 1,
  "causaienl": 1,
  "examinaicnt": 1,
  "Entasses": 1,
  "fenttres": 1,
  "aul": 1,
  "lappartemcnt": 1,
  "vicux": 1,
  "Iichus": 1,
  "moucloirs": 1,
  "aisserie": 1,
  "rue de\nChoiseul": 1,
  "trentel": 1,
  "Dcs": 1,
  "vard": 1,
  "Sourdun": 1,
  "aulrefois": 1,
  "Louisel": 1,
  "cortge": 1,
  "faubourg Saint-Martin": 1,
  "rue\nle Provence": 1,
  "Mostaganem": 1,
  "ILe": 1,
  "Aulcuil": 1,
  "thcatre": 1,
  "ayec": 1,
  "v0-": 1,
  "tinu": 1,
  "poussibere": 1,
  "Madme": 1,
  "arriere": 1,
  "fumnt": 1,
  "IlOS": 1,
  "Ellemontadedans": 1,
  "Algerie": 1,
  "Ilome": 1,
  "Imince": 1,
  "Grammont": 1,
  "courbe cn": 1,
  "dontj'": 1,
  "collge": 1,
  "relectoire": 1,
  "reseda": 1,
  "Ponts": 1,
  "Pe-\ncherie": 1,
  "Chhteauroux": 1
}