{
  "Cour": 23,
  "Maison": 17,
  "Bourdeille": 14,
  "Egypte": 13,
  "Rome": 11,
  "Villes": 11,
  "Pays": 11,
  "Ville": 10,
  "France": 10,
  "la France": 10,
  "Brant\u00f4me": 10,
  "Mareschal-de-Camp": 10,
  "Roy": 9,
  "Royaume": 8,
  "P\u00e9rigord": 8,
  "Romains": 7,
  "Bretagne": 7,
  "Montbron": 7,
  "d": 6,
  "Royaume de Naples": 6,
  "Savoye": 6,
  "Anglois": 6,
  "Romain": 5,
  "Roys": 5,
  "Ciel": 5,
  "Paris": 5,
  "Guyenne": 5,
  "Tour-blanche": 5,
  "Suisses": 5,
  "l\u2019ennemy": 5,
  "Egyptiens": 4,
  "Nil": 4,
  "d\u2019Egypte": 4,
  "Limosin": 4,
  "Lyon": 4,
  "Maison de Montbron": 4,
  "Mathas": 4,
  "Archiac": 4,
  "la Rochelle": 4,
  "Richemond": 4,
  "Brantome": 4,
  "Rubicon": 3,
  "S\u00e9nat": 3,
  "Perigord": 3,
  "Paradis": 3,
  "Boulogne": 3,
  "d\u2019Espagne": 3,
  "Seigneur": 3,
  "Bourdeaux": 3,
  "Grands": 3,
  "Maulevrier": 3,
  "Sertonville": 3,
  "Flandres": 3,
  "Nemours": 3,
  "l\u2019Abbaye": 3,
  "Epidaure": 2,
  "Pharfalle": 2,
  "Pl\u00e9b\u00e9yen": 2,
  "l\u2019Empire": 2,
  "Royaumes": 2,
  "Or": 2,
  "Patrie": 2,
  "Temples": 2,
  "Reyne": 2,
  "Couronne": 2,
  "Egyptien": 2,
  "Indien": 2,
  "Terre-Saincte": 2,
  "Mareschal de France": 2,
  "Grand-Maistre de l\u2019Artillerie": 2,
  "Maisons": 2,
  "Page": 2,
  "Terre": 2,
  "Naples": 2,
  "Espagnols": 2,
  "Italiens": 2,
  "Maisons de Guyenne": 2,
  "la Tour-blanche": 2,
  "Terres": 2,
  "l\u2019Op\u00e9ra": 2,
  "Espagnol": 2,
  "eille": 2,
  "Escosse": 2,
  "Foussan": 2,
  "Chasteau": 2,
  "Angleterre": 2,
  "Espagneuils": 2,
  "Pavie": 2,
  "Grandes": 2,
  "Seigneuries": 2,
  "Comt\u00e9": 2,
  "de France": 2,
  "Blaye": 2,
  "Place": 2,
  "Flamand": 2,
  "Jarnac": 2,
  "Dames": 2,
  "Le Ciel": 2,
  "d\u2019Aubeterre": 2,
  "Monastere des Defcalses": 2,
  "Tolose": 2,
  "Sarterre": 2,
  "Brian\u00e7on": 2,
  "Querci": 2,
  "Languedoc": 2,
  "Auvergne": 2,
  "Maison de la Douze": 2,
  "s": 2,
  "Pays de Borbonnois": 2,
  "Ve\u00fcure": 2,
  "BRANT\u00d4ME": 2,
  "Chasteau de Richemond": 2,
  "d\u2019Allemagne": 2,
  "Chastelleraud": 2,
  "Italie": 2,
  "Ville de Brant\u00f4me": 2,
  "Baron de Richemond": 2,
  "Debvoir": 2,
  "Souverain": 2,
  "l\u2019Estat": 2,
  "Chefs": 2,
  "Village": 2,
  "Lansquenets": 2,
  "Royaux": 2,
  "Gendarmerie": 2,
  "Mareschal": 2,
  "Camp": 2,
  "Logis": 2,
  "Tombeau de": 2,
  "Reminy": 1,
  "Ville de Brundufie": 1,
  "Marseille": 1,
  "Pompe\u00efans": 1,
  "Lybie": 1,
  "Pharsalle": 1,
  "Public": 1,
  "iy Or": 1,
  "Latin": 1,
  "Feu": 1,
  "Pharsale": 1,
  "ilte": 1,
  "Grece": 1,
  "d\u2019Estrangers": 1,
  "Estranger": 1,
  "Arm\u00e9nien": 1,
  "Barbare": 1,
  "Romaine": 1,
  "l\u2019Estat Romain": 1,
  "Gaule": 1,
  "Dieux": 1,
  "Mars": 1,
  "Terres Thessalicques": 1,
  "Rostres": 1,
  "Cit\u00e9 de Rome": 1,
  "Bandes": 1,
  "Dieu": 1,
  "\u00efadvantagey": 1,
  "haut Orient": 1,
  "Dames Romaines": 1,
  "E R A N T 0 AI E": 1,
  "enIhoufiafme": 1,
  "Phar\u00eealle": 1,
  "l": 1,
  "Ptolom\u00e9es": 1,
  "l\u2019Egyptien": 1,
  "Roma": 1,
  "Ville de Paretonie": 1,
  "l\u2019Empire Romain": 1,
  "l\u2019Egy": 1,
  "l\u2019Egypte": 1,
  "\u201e": 1,
  "R\u00e9gence": 1,
  "\u201e Royaume": 1,
  "\u00e9e": 1,
  "": 1,
  "OPUSCULES DITERS": 1,
  "Indienne": 1,
  "Tyrien": 1,
  "Egyp": 1,
  "tiens": 1,
  "Germanie": 1,
  "mer Rouge": 1,
  "l\u2019Egypte-mes": 1,
  "l\u2019Isle de Mero\u00e9": 1,
  "Falerne": 1,
  "d\u2019Ethiopie": 1,
  "Provinces": 1,
  "Loy d": 1,
  "R\u00e9gion": 1,
  "d\u2019Ordonnance": 1,
  "-G\u00e9n\u00e9ral": 1,
  "S\u00e9neschal": 1,
  "Vi": 1,
  "J\u00efsnnes": 1,
  "Poictou": 1,
  "Fou": 1,
  "Pages des Reynes": 1,
  "Princesses": 1,
  "des Cordeliers": 1,
  "l\u2019Eglise des Cordeliers": 1,
  "Foyez": 1,
  "la Cour": 1,
  "d\u2019Armagnac": 1,
  "Romanie": 1,
  "Ben": 1,
  "C i": 1,
  "Fran\u00e7ois": 1,
  "Ravenne": 1,
  "Mar": 1,
  "Marignan": 1,
  "Milan": 1,
  "Maison du Lude": 1,
  "Maisons de Guye": 1,
  "d\u2019Amville": 1,
  "che": 1,
  "d\u2019Angoulefme": 1,
  "leS\u00e9pulchre d\u2019Amville": 1,
  "Fontevaux": 1,
  "Cercles": 1,
  "Paroisse": 1,
  "Maison de Guyenne": 1,
  "Cremone": 1,
  "Italien": 1,
  "Piedmont": 1,
  "la Feuillade": 1,
  "Sainctonge": 1,
  "Feuillade": 1,
  "Chasteau de Montmelian": 1,
  "Ardres": 1,
  "d\u2019Angleterre": 1,
  "l\u2019Eglise de St. Paul": 1,
  "Londres": 1,
  "Juy": 1,
  "Gascons": 1,
  "Reyne d\u2019Angleterre": 1,
  "B R {1 N TOM E": 1,
  "elier": 1,
  "Baronnies d\u2019Angoulmois": 1,
  "Damas Iiluilres": 1,
  "Seigneurs": 1,
  "Comte": 1,
  "de P\u00e9rigord": 1,
  "Vifcomtes d\u2019Aunay": 1,
  "Barons": 1,
  "Royan": 1,
  "Chef-boutonne": 1,
  "Sainct-Megrin": 1,
  "Mortague": 1,
  "Vifcomte de Chasteaudun": 1,
  "d\u2019Aunay": 1,
  "Beauvoyfin": 1,
  "Poi\u00e9tiers": 1,
  "Gravelines": 1,
  "Viscomtez & Baronnies de Bour- deille, Archiac": 1,
  "la Tour blanche": 1,
  "Vifcomtez & Baronnies": 1,
  "Romans": 1,
  "Grande Bretagne": 1,
  "Cha": 1,
  "MONTBRON": 1,
  "Seigneur de Montbron": 1,
  "Seigneurs de Montbron": 1,
  "Fournoue": 1,
  "Mont- bron": 1,
  "Termes": 1,
  "Comte d\u2019Ayguemond": 1,
  "Italiennes": 1,
  "Efpagnolles": 1,
  "Palladins": 1,
  "Chevalliers": 1,
  "Roys de France": 1,
  "\u2019Anjou": 1,
  "Garillan": 1,
  "andre": 1,
  "Marol": 1,
  "Jalo": 1,
  "Jalon": 1,
  "Metz": 1,
  "Hesdin": 1,
  "Montcontour": 1,
  "Breragne": 1,
  "Dames de France": 1,
  "OPUSCULES DIFERS": 1,
  "Espagnolle": 1,
  "Italienne": 1,
  "de la France": 1,
  "Annebon": 1,
  "Champs Elysiens": 1,
  "Enfer": 1,
  "Ba": 1,
  "l\u2019Angoulmois": 1,
  "Montpezac d\u2019Agen\u00e8s": 1,
  "Reyne-Mer": 1,
  "la Tour-blanc": 1,
  "Chasteau d\u2019Archiac": 1,
  "L\u2019ONCLE": 1,
  "LA NIEPCE": 1,
  "L": 1,
  "ONCLE": 1,
  "champ Elysien": 1,
  "UBETERRE": 1,
  "PAS": 1,
  "ANT": 1,
  "Mont de Sainct-IVIichel": 1,
  "inct-": 1,
  "n": 1,
  "d\u2019Auvergne": 1,
  "d\u2019E- OPUSCULES DIVERS": 1,
  "d\u2019Angoulmois": 1,
  "Maison de Bourd": 1,
  "Maison de Lauzun": 1,
  "Maison grande d\u2019Eflifrac": 1,
  "Lude": 1,
  "Villars": 1,
  "Mont- pezat": 1,
  "Sieur": 1,
  "Bourrez": 1,
  "Cou": 1,
  "l\u2019Aichcveique de Rouen": 1,
  "Maison de": 1,
  "Seigneur d\u2019Auvergne": 1,
  "Baron du Pont & du Chasteau": 1,
  "Gentils-Hommes": 1,
  "St. Bonnet": 1,
  "(*) Ici Penacor": 1,
  "Pennacon": 1,
  "Blois": 1,
  "Alen\u00e7on": 1,
  "Duc de Savoye": 1,
  "Turin": 1,
  "Tour": 1,
  "Chartres": 1,
  "d\u2019Amyens": 1,
  "Ostende": 1,
  "Rochandry": 1,
  "Gondras": 1,
  "Loude": 1,
  "Magny": 1,
  "Charolois": 1,
  "Indes Occidentales": 1,
  "Indiens": 1,
  "Chasteau de Mon- targis": 1,
  "lesSuisses": 1,
  "Allemands": 1,
  "Canton de Soleurre": 1,
  "Chasteau de Brantome": 1,
  "Archevesque": 1,
  "Pampelune": 1,
  "Rhodes": 1,
  "Drone": 1,
  "Fontarabie": 1,
  "Royaume des Taupes": 1,
  "Cap de Dious": 1,
  "Gascon": 1,
  "Seigneur d\u2019Albret": 1,
  "I'": 1,
  "Cours des Princes": 1,
  "Ba AA'\u00ab TOME": 1,
  "Baron": 1,
  "Mommoreau": 1,
  "Conseigneur": 1,
  "BRANT\u00d4ME usuf": 1,
  "Chevallier de l\u2019": 1,
  "Chapelle": 1,
  "eigne": 1,
  "Vivonne": 1,
  "Ville de Belis": 1,
  "Pignon": 1,
  "Barbarie": 1,
  "Espagne": 1,
  "Chambre": 1,
  "Moulin de la Rode": 1,
  "Paroisse de Sr. Crespin": 1,
  "Houlou": 1,
  "Belefine": 1,
  "l\u2019Abbaye de Brant\u00f4me": 1,
  "Tourblanche": 1,
  "S\u00e9crecaires": 1,
  "Pages": 1,
  "Abb\u00e9 Commandataire": 1,
  "St. Sevrin": 1,
  "Poitou": 1,
  "St. Vincent-l\u00e8s-Xainc- tes": 1,
  "Doyen\u00e9 de St. Yriers": 1,
  "Limousin": 1,
  "Prior\u00e9 de Royan": 1,
  "d\u2019Eglise": 1,
  "Princes": 1,
  "Borde": 1,
  "Confeigneurie de Brantome": 1,
  "Peraux": 1,
  "Bour": 1,
  "-": 1,
  "Gentil-Homme": 1,
  "l\u2019Evesque": 1,
  "Majestez": 1,
  "Eve": 1,
  "ch\u00e9": 1,
  "quatre Mandiants": 1,
  "Hostel-Dieu de Paris": 1,
  "de Brant\u00f4me": 1,
  "Saunier": 1,
  "Terre de": 1,
  "Cour de Bour- deaux": 1,
  "Provence": 1,
  "Vafouziere": 1,
  "Biblioth\u00e8": 1,
  "que": 1,
  "Espagnolles": 1,
  "Places": 1,
  "Charge": 1,
  "Cour Pr\u00e9si": 1,
  "Cour Pr\u00e9sidiale de P\u00e9rigueux": 1,
  "Brancome": 1,
  "Cherebaud": 1,
  "Abbaye": 1,
  "CEJOURD\u2019HUY": 1,
  "Chasteau de": 1,
  "Confeigneur": 1,
  "Confeigneur de Brant\u00f4me": 1,
  "Chasteau de Brant\u00f4me": 1,
  "No": 1,
  "Royal": 1,
  "Chaftelleraud": 1,
  "Perigueux": 1,
  "Chapelle de Richemond": 1,
  "Chasteau de la Tour-blanche": 1,
  "MARESCNAL-DE-CAMP": 1,
  "VOSTRE MAJEST\u00c9": 1,
  "Tob\u00e9yj": 1,
  "J": 1,
  "-Estat": 1,
  "Estat": 1,
  "G\u00e9": 1,
  "Ia-dicte Ville": 1,
  "-de-Camp": 1,
  "l\u2019Arm\u00e9e": 1,
  "Colonnel": 1,
  "Maistre-de-Camp": 1,
  "Mareschaux- de -Camp": 1,
  "Mareschalde Camp": 1,
  "Mareschal de-Camp": 1,
  "GrandMaistre de l\u2019Artillerie": 1,
  "DERf/OIR": 1,
  "Mareschaux-deCamp": 1,
  "-Lo": 1,
  "Mareschalde-Camp": 1,
  "B": 1,
  "Villages": 1,
  "Cavallerie": 1,
  "Chevaux-l\u00e9gers": 1,
  "DV MARESCHAL-DE- CAMP. 2ii": 1,
  "\u2019ennemy": 1,
  "Maistres- Camp": 1,
  "aillon": 1,
  "Marexchalde-Camp": 1,
  "fJYERAIN": 1,
  "Pays de l\u2019": 1,
  "my": 1,
  "Pays de l\u2019ennemy": 1,
  "Mareschaux-de-Camp": 1,
  "Col": 1,
  "-Camp": 1,
  "Harquebuziers": 1,
  "aval": 1,
  "Aydes": 1,
  "LVlarcrdml-de-Camp": 1,
  "Chef": 1,
  "Ma- reschal-de-Camp": 1,
  "Pionniers": 1,
  "f": 1,
  "de Navarre": 1,
  "Tombeau de Madame": 1,
  "Tombeau": 1,
  "ETERRE": 1,
  "Ghaf\u00eeeau de Brant\u00f4me": 1,
  "BRANTOME": 1,
  "El": 1,
  "de-Camp": 1,
  "Souverai.n": 1,
  "Kj\u00e9ne": 1,
  "Camp.": 1,
  "Arm\u00e9e": 1
}