{
  "spacy-lg-3.7.5_TesseractFra-PNG": {
    "EN-occ": 90,
    "EN-type": 58
  },
  "spacy-lg-3.7.5_kraken": {
    "EN-occ": 113,
    "EN-type": 81
  },
  "spacy-lg-3.7.5_REF": {
    "EN-occ": 61,
    "EN-type": 31
  },
  "spacy-lg-3.7.5_ACCMAJ": {
    "EN-occ": 9,
    "EN-type": 9
  },
  "spacy-md-3.7.5_TesseractFra-PNG": {
    "EN-occ": 74,
    "EN-type": 55
  },
  "spacy-md-3.7.5_kraken": {
    "EN-occ": 99,
    "EN-type": 82
  },
  "spacy-md-3.7.5_REF": {
    "EN-occ": 52,
    "EN-type": 34
  },
  "spacy-md-3.7.5_ACCMAJ": {
    "EN-occ": 9,
    "EN-type": 9
  },
  "spacy-sm-3.7.5_TesseractFra-PNG": {
    "EN-occ": 155,
    "EN-type": 70
  },
  "spacy-sm-3.7.5_kraken": {
    "EN-occ": 90,
    "EN-type": 58
  },
  "spacy-sm-3.7.5_REF": {
    "EN-occ": 69,
    "EN-type": 36
  },
  "spacy-sm-3.7.5_ACCMAJ": {
    "EN-occ": 9,
    "EN-type": 9
  },
  "spacy-lg-2.3.5_TesseractFra-PNG": {
    "EN-occ": 62,
    "EN-type": 44
  },
  "spacy-lg-2.3.5_kraken": {
    "EN-occ": 69,
    "EN-type": 57
  },
  "spacy-lg-2.3.5_REF": {
    "EN-occ": 40,
    "EN-type": 29
  },
  "spacy-lg-2.3.5_ACCMAJ": {
    "EN-occ": 9,
    "EN-type": 9
  },
  "spacy-md-2.3.5_TesseractFra-PNG": {
    "EN-occ": 63,
    "EN-type": 49
  },
  "spacy-md-2.3.5_kraken": {
    "EN-occ": 66,
    "EN-type": 53
  },
  "spacy-md-2.3.5_REF": {
    "EN-occ": 42,
    "EN-type": 30
  },
  "spacy-md-2.3.5_ACCMAJ": {
    "EN-occ": 9,
    "EN-type": 9
  },
  "spacy-sm-2.3.5_TesseractFra-PNG": {
    "EN-occ": 91,
    "EN-type": 58
  },
  "spacy-sm-2.3.5_kraken": {
    "EN-occ": 83,
    "EN-type": 65
  },
  "spacy-sm-2.3.5_REF": {
    "EN-occ": 55,
    "EN-type": 43
  },
  "spacy-sm-2.3.5_ACCMAJ": {
    "EN-occ": 9,
    "EN-type": 9
  },
  ".csv5000.bio_ACCMAJ": {
    "EN-occ": 9,
    "EN-type": 9
  },
  "une-vie.csv5000.bio_ACCMAJ": {
    "EN-occ": 0,
    "EN-type": 0
  }
}