{
  "Coucy": 22,
  "Laon": 20,
  "Anizy": 16,
  "Bussy": 15,
  "Cour": 12,
  "Sissone": 11,
  "I": 11,
  "de-": 9,
  "Paris": 9,
  "P": 9,
  "Picarde": 9,
  "Picardie": 7,
  "Rochefort": 7,
  "el": 7,
  "Bussy-Lameth": 6,
  "Versailles": 5,
  "en-": 5,
  "Croyez": 5,
  "Estr\u00e9es": 5,
  "Chavignon": 5,
  "Bussy-La-": 4,
  "Mesdemoiselles": 4,
  "\u00celes": 4,
  "Roucy": 3,
  "E": 3,
  "Ursulines": 3,
  "Soissons": 3,
  "Corcy": 3,
  "mademo\u00efselle": 2,
  "l\u00fci": 2,
  "jura": 2,
  "Hautefort": 2,
  "Voulez": 2,
  "Heudicourt": 2,
  "Fontainebleau": 2,
  "Dites": 2,
  "\u00c2llez": 2,
  "Rhin": 2,
  "Flandre": 2,
  "soleil": 2,
  "Fe": 2,
  "Etil": 2,
  "Pi-": 2,
  "Couey": 2,
  "\u00c9cu de France": 2,
  "Villers-Cotterets": 2,
  "J\u00e9": 2,
  "Sis-": 2,
  "Croix-Blanche": 2,
  "ba\u00eflli": 2,
  "Biblioth\u00e8que nationale de France\n\f\n11 Gallica\n\n \n\nComtesse Dash": 1,
  "Biblioth\u00e8que nationale de France": 1,
  "rue Saint-Honor\u00e9": 1,
  "lacour": 1,
  "amsi": 1,
  "Ei": 1,
  "\u00cele": 1,
  "C\u00e9": 1,
  "Rou-": 1,
  "Cy": 1,
  "Champagne": 1,
  "|": 1,
  "ICI": 1,
  "Tours blanc": 1,
  "Venise": 1,
  "ch\u00e2teau\nde Versailles": 1,
  "la France": 1,
  "Tonnay-Charente": 1,
  "Orl\u00e9ans": 1,
  "accoutuma": 1,
  "Carrousel": 1,
  "Mortagne": 1,
  "Mothe": 1,
  "\u00ce": 1,
  "Roche\u00efort": 1,
  "jardin des Hesp\u00e9rides": 1,
  "Rouey": 1,
  "La Mothe": 1,
  "Tours": 1,
  "meur\u00e9": 1,
  "Allemagne": 1,
  "Cherchez": 1,
  "el sur-": 1,
  "ch\u00e2teau de Versailles": 1,
  "Klle": 1,
  "Henrietie": 1,
  "Joux": 1,
  "tourm\u00e9nter": 1,
  "Conscience": 1,
  "CRETE": 1,
  "Ou-": 1,
  "Pignerol": 1,
  "Cour de France": 1,
  "Argus": 1,
  "\u0178": 1,
  "Ondit": 1,
  "Espagne": 1,
  "noncerai": 1,
  "Tenez": 1,
  "Ilsortit": 1,
  "L\u00f4l": 1,
  "c\u00e9": 1,
  "th\u00e9\u00e2tre de\n": 1,
  "Demandes": 1,
  "Etils": 1,
  "r\u00e9gimenis de\nChampagne": 1,
  "Navarre": 1,
  "Normandie": 1,
  "couvent des Ursulines": 1,
  "Made-": 1,
  "pir": 1,
  "diamans": 1,
  "Louis-le-Grand": 1,
  "celaient": 1,
  "Terre-Sainte": 1,
  "Saint-Jean-d'Acre": 1,
  "abbaye de Pr\u00e9monir\u00e9": 1,
  "Louis-le-Gros": 1,
  "maine": 1,
  "Bouvines": 1,
  "de France": 1,
  "Dreux de Cr\u00e8vec\u0153ur": 1,
  "Aixin": 1,
  "Lanissecourt": 1,
  "Clany": 1,
  "Thurin": 1,
  "Ansizy-le-Ch\u00e2tel": 1,
  "Bou-": 1,
  "chavannes": 1,
  "Hennecourt": 1,
  "Bussy de Clermont d'Amboise": 1,
  "Bussy d\u2019Am-": 1,
  "ee md": 1,
  "entr'au-": 1,
  "for\u00eat de Pr\u00e9montr\u00e9": 1,
  "Aniy": 1,
  "| vince": 1,
  "A\u00efnsi": 1,
  "riette": 1,
  "y\u00eaque": 1,
  "Est-elle": 1,
  "Gr\u00e2ces": 1,
  "cel": 1,
  "Accoutum\u00e9e": 1,
  "SOINS": 1,
  "actionindigne": 1,
  "pagna": 1,
  "Na-": 1,
  "Efc'": 1,
  "mo\u00eff": 1,
  "Ver-": 1,
  "\u00cf": 1,
  "Soyons": 1,
  "Sais": 1,
  "Prononcez": 1,
  "\u00cfls": 1,
  "Convenez": 1,
  "Cherche": 1,
  "toul": 1,
  "ch\u00e2teau d'Anizy": 1,
  "tourme\u00f1ts": 1,
  "M\u00f4n": 1,
  "Partez": 1,
  "\u00ce]s": 1,
  "PETITE A": 1,
  "comiesse": 1,
  "st Avec M": 1,
  "Jouer": 1,
  "Vi-": 1,
  "Co": 1,
  "parc d'Anizy": 1,
  "Nousnousamuserons": 1,
  "ch\u00e2teau de Pimon": 1,
  "confian\u00e9e": 1,
  "place de Jo-": 1,
  "Bourgogne": 1,
  "C\u00fccy": 1,
  "lieuteuant-crimi": 1,
  "\u00c9cu\nde France": 1,
  "I\u00e0": 1,
  "PINON": 1,
  "a-\nLil": 1,
  "pays-c1": 1,
  "Providence": 1,
  "\u0178 a": 1,
  "nant": 1,
  "Al": 1,
  "Carm\u00e9lites": 1,
  "ee \u2014": 1,
  "ES te D Pt": 1,
  "Fayel": 1,
  "Pi\u00fbt": 1,
  "T\u00e2chez": 1,
  "Ft": 1,
  "Louison": 1,
  "bres": 1,
  "Saint-Quentin": 1,
  "M": 1,
  "lout": 1,
  "Al\nbret": 1,
  "Vousvoulezquitter": 1,
  "Trouvez-": 1,
  "m'\u2019\u00e9chapper": 1,
  "Im-": 1,
  "\u00e9pondre": 1,
  "D59": 1,
  "Ti\u00e9n": 1,
  "p\u00e9rsontie": 1,
  "\u00ce\u00cfls": 1,
  "\u00cels": 1,
  "lombier": 1,
  "jaais": 1,
  "Jen'": 1,
  "Adien": 1,
  "fe": 1,
  "tilf": 1,
  "l\u00e9 f6s\u00c9": 1,
  "h\u00e4rdi\u00e8sse": 1,
  "Yage": 1,
  "sOhe": 1,
  "Madarmne": 1,
  "HN": 1,
  "D\u00e9sirez": 1,
  "C\u00e9s": 1,
  "Cha\u00efl\u00e9s": 1,
  "Ama-": 1,
  "Ell\u00e9": 1,
  "ven": 1,
  "Laineth": 1,
  "Noyon": 1,
  "\u00c6": 1,
  "r\u00e9monie": 1,
  "Courval": 1,
  "Bussy d'Am-": 1,
  "Amboise": 1,
  "IL": 1,
  "vingtans": 1,
  "quellesil": 1,
  "Lambertremit": 1,
  "carioledeM. C\u0153ur-de-Roy": 1,
  "Or-": 1,
  "manger": 1,
  "Delette": 1,
  "Pour-": 1,
  "Boh\u00e9miens": 1,
  "\u00c9": 1,
  "Tout-\u00e0-coup": 1,
  "Croyez-": 1,
  "Montrez": 1,
  "France": 1,
  "Kexhortait": 1,
  "cure-denis": 1,
  "ma\u00efiiresse": 1
}