{
  "C\u0153ur-Loyal": 156,
  "Indiens": 108,
  "\u00c9lan-Noir": 46,
  "T\u00eate-d'Aigle": 35,
  "Mexicains": 29,
  "Ramon": 29,
  "Indien": 25,
  "Comanches": 19,
  "Peaux-Rouges": 18,
  "Canadien": 18,
  "Aigle": 13,
  "Le C\u0153ur-Loyal": 13,
  "Le C\u0153ur": 11,
  "\u00c9tats-Unis": 9,
  "Am\u00e9ricains": 9,
  "trappes": 9,
  "Babillard": 9,
  "\u2013\u00a0Bien": 9,
  "Aguilar": 8,
  "\u2013\u00a0Oui": 8,
  "Mexico": 8,
  "Mexique": 7,
  "Rafa\u00ebl": 7,
  "\u2013\u00a0Non": 7,
  "Belhumeur": 7,
  "l'Am\u00e9rique": 6,
  "Hermosillo": 6,
  "Do\u00f1a Jesusita": 6,
  "Venez": 6,
  "Blancs": 6,
  "N\u00e8gre": 6,
  "Allons": 6,
  "Comanche": 6,
  "Ouest": 5,
  "Do\u00f1a Luz": 5,
  "\u2013\u00a0": 5,
  "Am\u00e9rique": 4,
  "Le soleil": 4,
  "terre": 4,
  "Allez": 4,
  "Soleil": 4,
  "Espagnols": 3,
  "rio Gila": 3,
  "sierra Madre": 3,
  "Sonora": 3,
  "Guaymas": 3,
  "Arr\u00eatez": 3,
  "Tiens": 3,
  "le soleil": 3,
  "I": 3,
  "Arkansas": 3,
  "piste des Comanches": 3,
  "voulez": 3,
  "\u2013\u00a0Est": 3,
  "Luz": 3,
  "Ooah": 3,
  "le Soleil": 3,
  "\u00c9tat": 2,
  "Pacifique": 2,
  "Pawnees": 2,
  "Apaches": 2,
  "Prompt": 2,
  "buffalos": 2,
  "Blanc": 2,
  "Providence": 2,
  "II": 2,
  "Europe": 2,
  "Ph\u00e9b\u00e9": 2,
  "Combien": 2,
  "VI": 2,
  "Gardez": 2,
  "\u2013\u00a0Quels": 2,
  "Les Indiens": 2,
  "bah": 2,
  "Tr\u00eave": 2,
  "Peaux": 2,
  "\u2013\u00a0Tr\u00e8s bien": 2,
  "Plateros": 2,
  "Arriv\u00e9s": 2,
  "Se\u00f1orita": 2,
  "Regardez": 2,
  "Qu\u00e9bec": 2,
  "Sommes": 2,
  "lune": 2,
  "Parlez": 2,
  "Eus\u00e9bio": 2,
  "Partez": 2,
  "camp des Mexicains": 2,
  "mignonne": 2,
  "R\u00e9pondez": 2,
  "Chiens": 2,
  "Fran\u00e7ais": 2,
  "Apacheria": 2,
  "les Incas": 1,
  "l'Europe": 1,
  "\u00c9tats": 1,
  "\u00c9tat de Sonora": 1,
  "golfe de Californie": 1,
  "Durango": 1,
  "\u00c9tats de Durango": 1,
  "Guadalajara": 1,
  "Pimas": 1,
  "Opatas": 1,
  "Montagne": 1,
  "Gambusinos": 1,
  "Rosario": 1,
  "rue du Rosaire": 1,
  "Cerro": 1,
  "Ciboto": 1,
  "Prends": 1,
  "P\u00e9rou": 1,
  "Cordoue": 1,
  "Derri\u00e8re": 1,
  "Panama": 1,
  "Cortez": 1,
  "jardin des Oliviers": 1,
  "Sermon": 1,
  "Albaceyte": 1,
  "pasto": 1,
  "Mettez": 1,
  "\u00c9coutez": 1,
  "\u2013\u00a0Tuez-moi": 1,
  "\u2013\u00a0Rentrez": 1,
  "\u00e9pargnez-les-moi": 1,
  "La Providence": 1,
  "\u2013\u00a0Jesusita": 1,
  "Mississippi": 1,
  "Canadienne": 1,
  "rivi\u00e8re Rouge": 1,
  "Delawares": 1,
  "Cricks": 1,
  "Osages": 1,
  "Pieds-Noirs": 1,
  "Assiniboins": 1,
  "Lune": 1,
  "Mocksens": 1,
  "Veillerai": 1,
  "soleil": 1,
  "\u2013\u00a0Bien\u00a0!": 1,
  "du Nord": 1,
  "Le C\u0153ur-Loyal sourit": 1,
  "Pensant": 1,
  "Rapportez": 1,
  "\u2013\u00a0Essayons": 1,
  "bois-chandelle": 1,
  "gambusinos demi-sang": 1,
  "Jupiter": 1,
  "Bermudez": 1,
  "Am\u00e9ricaines": 1,
  "\u00c9lev\u00e9e": 1,
  "Guadeloupe": 1,
  "Linn\u00e9e": 1,
  "\u2013\u00a0Tenez": 1,
  "Indien Osage": 1,
  "L'Indien": 1,
  "Nehu nutah": 1,
  "H\u00e2tez": 1,
  "H\u00e2tons": 1,
  "Angleterre": 1,
  "Am\u00e9rique du Nord": 1,
  "pacifique": 1,
  "\u00c9tats barbaresques": 1,
  "R\u00e9gences d'Alger": 1,
  "Tripoli": 1,
  "Conf\u00e9d\u00e9ration": 1,
  "Rouges": 1,
  "Cuivr\u00e9s": 1,
  "Utique": 1,
  "Syracuse": 1,
  "Rome": 1,
  "Carthage": 1,
  "Blancs-Yeux": 1,
  "Acropolis": 1,
  "\u2013\u00a0Sont": 1,
  "Anglais": 1,
  "H\u00e2te-toi": 1,
  "Bourreau": 1,
  "Sept": 1,
  "Coq": 1,
  "\u2013\u00a0Pardieu\u00a0!": 1,
  "Bonjour": 1,
  "\u2013\u00a0Bien, ma fille": 1,
  "l'Afrique": 1,
  "XI": 1,
  "Reculerais-tu": 1,
  "songerais-tu": 1,
  "Ouaktehno": 1,
  "Tenez": 1,
  "Buffalo": 1,
  "XII": 1,
  "couvent de la Merced": 1,
  "San Agustin": 1,
  "aventure de Mexico": 1,
  "\u2013\u00a0Excellent": 1,
  "cath\u00e9drale de Mexico": 1,
  "\u2013\u00a0Rien": 1,
  "Attendre": 1,
  "\u2013\u00a0Maintenant": 1,
  "vieille Europe": 1,
  "\u2013\u00a0Kennedy": 1,
  "Carai": 1,
  "Conseille": 1,
  "Attends": 1,
  "Charmant": 1,
  "\u2013\u00a0Que": 1,
  "Rassurez": 1,
  "\u2013\u00a0Cher": 1,
  "La T\u00eate": 1,
  "T\u00eate-Blanche": 1,
  "compagne": 1,
  "Espagnol": 1,
  "prierez": 1,
  "Viens": 1,
  "Ginetes mexicains": 1,
  "Eshis": 1,
  "Le Soleil": 1,
  "Finissons-en": 1,
  "Vais": 1,
  "alluma": 1,
  "Vaincue": 1,
  "Quelles": 1,
  "\u2013\u00a0Belhumeur": 1,
  "Salvator Rosa": 1,
  "Russe": 1,
  "Chinois": 1,
  "Oc\u00e9an": 1,
  "France": 1,
  "us": 1,
  "Rendez": 1,
  "\u2013\u00a0Bah\u00a0!": 1,
  "\u2013\u00a0Diable": 1,
  "\u2013\u00a0Pas": 1,
  "besogne": 1,
  "Oubli\u00e9": 1,
  "\u2013\u00a0Figurez": 1,
  "muette": 1,
  "Cach\u00e9": 1,
  "Prenez-le": 1,
  "grotte du Vert-de-gris": 1,
  "Bison": 1,
  "Les Comanches": 1,
  "Convaincu": 1,
  "Rest\u00e9": 1,
  "Vert-de-Gris": 1,
  "Pardonnez": 1,
  "Cr\u00e9ateur": 1,
  "Avez": 1,
  "Moi-m\u00eame": 1,
  "\u2013\u00a0Bah": 1,
  "Jeunes": 1,
  "Indiennes": 1,
  "\u2013\u00a0Esp\u00e9rer": 1,
  "\u2013\u00a0Diable\u00a0!": 1,
  "D\u00e9cid\u00e9ment": 1,
  "coquins": 1,
  "Cara\u00ef": 1,
  "N\u00e8gre Jupiter": 1,
  "\u2013\u00a0Hol\u00e0": 1,
  "Certain": 1,
  "Chose": 1,
  "Grande": 1,
  "\u2013\u00a0Tue-moi": 1,
  "wampums": 1,
  "Montrons": 1,
  "manche": 1,
  "Pas": 1,
  "Essayez": 1,
  "r\u00e9pondrez": 1,
  "Voulez": 1,
  "\u2013\u00a0Relevez": 1,
  "Pouss\u00e9": 1,
  "oc\u00e9an Pacifique": 1,
  "r\u00e9pliquai-je na\u00efvement": 1,
  "jeun": 1,
  "tercushenan": 1
}