{
  "l\u2019": 102,
  "Florence": 19,
  "qu\u2019": 18,
  "s\u2019": 17,
  "WILMINA": 16,
  "Lazaro": 15,
  "Wilmina": 12,
  "Colonia": 11,
  "C\u00e9zarini": 11,
  "Jui": 10,
  "j\u2019": 9,
  "A": 9,
  "F": 7,
  "Naples": 6,
  "Villa-Rosa": 6,
  "Apennins": 6,
  "Gallica": 4,
  "I": 4,
  "Providence": 4,
  "Venez": 4,
  "Laurentino": 4,
  "S": 3,
  "\u00cele": 3,
  "Er": 3,
  "ger": 3,
  "d\u2019": 3,
  "el": 3,
  "Hottentots": 3,
  "Raoul": 3,
  "L": 2,
  "ee": 2,
  "\u00c8": 2,
  "Azoly": 2,
  "J": 2,
  "Allemande": 2,
  "Pise": 2,
  "Fe": 2,
  "Pas": 2,
  "\u00ce": 2,
  "Mas": 2,
  "rs": 2,
  "FE": 2,
  "!": 2,
  "A varello": 2,
  "trouverez": 2,
  "ca": 2,
  "Alberu": 2,
  "Montagne": 2,
  "Toscane": 2,
  "so": 2,
  "palais Colonia": 2,
  "E": 2,
  "Let": 2,
  "l'Italie": 2,
  "signor": 2,
  "Europe": 2,
  "ch\u00e2teau des Souvenirs": 2,
  "Mile": 1,
  "Ja": 1,
  "\u00ce.": 1,
  "Lrrepvre-La-Rocux": 1,
  "at": 1,
  "x L": 1,
  "PARIS": 1,
  "Quai des Augustins": 1,
  "Ki\n\n+ veu D": 1,
  "s\u2019'approcha": 1,
  "WiLMina": 1,
  "Aa": 1,
  "N": 1,
  "Luco": 1,
  "Sotvenirs": 1,
  "sur-le-champ": 1,
  "st\n\nWW ILMIN": 1,
  "Sons": 1,
  "suivit": 1,
  "ceux--": 1,
  "Iqui\u00e9taie": 1,
  "Wilnina": 1,
  "Teri": 1,
  "261 Lo\u00e9e": 1,
  "Hanszles": 1,
  "jare": 1,
  "Tuit": 1,
  "HI": 1,
  "Tenclos": 1,
  "Pourrem\u00e9dier": 1,
  "b\u00e2timens": 1,
  "Las": 1,
  "A\n\nhe tm: \u00c0. fe": 1,
  "Maisilguetta": 1,
  "Ju-": 1,
  "RPG": 1,
  "L\u2019": 1,
  "Ta": 1,
  "Shs": 1,
  "ts Fe": 1,
  "Vic=\n\nwii\u00e9": 1,
  "t\u00e9iDLE": 1,
  "Aivarello": 1,
  "A\n\n": 1,
  "Ebsca": 1,
  "Selretirent \u00eat\n": 1,
  "MI1EMIEN": 1,
  "coup-:elle-": 1,
  "infortun\u00e9e Fulvia": 1,
  "set": 1,
  "Ts mm + A AN": 1,
  "Lons": 1,
  "chambre de la-jeune": 1,
  "Fulvia": 1,
  "F\u00e4pp\u00e9lant": 1,
  "de+": 1,
  "\u2014 - Elle": 1,
  "mans": 1,
  "On l\u2019": 1,
  "Allez": 1,
  "volez": 1,
  "soleil": 1,
  "Elisca": 1,
  "Ja Providence": 1,
  "demanda-t-elle;:croyez-": 1,
  "Enle": 1,
  "\u00e9tat": 1,
  "M": 1,
  "M'A ES": 1,
  "J'": 1,
  "\u00e9\u2019": 1,
  "Mille": 1,
  "Maux": 1,
  "Jette": 1,
  "Tenez": 1,
  "-WILMINA": 1,
  "G\u00e9": 1,
  "HR": 1,
  "ais": 1,
  "st\n\n+": 1,
  "eniends-e": 1,
  "Mal-": 1,
  "PART A": 1,
  "MS": 1,
  "Malsina": 1,
  "Pautre": 1,
  "gure": 1,
  "Wihni-": 1,
  "comment\u2019": 1,
  "M\u00e4l\u00ffinai": 1,
  "Jens": 1,
  "Ja-\n\nloux": 1,
  "Hop": 1,
  "L\u00e9\u2019": 1,
  "j Jour": 1,
  "lPobs-": 1,
  "Noix": 1,
  "Lazaro l\u2019": 1,
  "Votre \u00e2ge": 1,
  "Cal\u00e0brais": 1,
  "Ile": 1,
  "votis": 1,
  "\u00cele soigner": 1,
  "j\n\n\u0178": 1,
  "Couro": 1,
  "fut-1l": 1,
  "Pacca-": 1,
  "Vaux": 1,
  "ER": 1,
  "a1": 1,
  "H\u00e9bien": 1,
  "Pun": 1,
  "P": 1,
  "sur-le-ch\u00e4amp": 1,
  "WIiLMINA": 1,
  "S1": 1,
  "voie du\nsalut n.\n\nWilmina": 1,
  "L\u00e4azaro": 1,
  "PTE": 1,
  "Jets": 1,
  "chambre de la comiesse": 1,
  "Bertrude": 1,
  "L\u00e2che": 1,
  "PA \u00c0": 1,
  "Ce -.": 1,
  "For es": 1,
  "Faffablir": 1,
  "sayai": 1,
  "Furteux": 1,
  "Jui teuir parole": 1,
  "AveOHIX": 1,
  "nuen": 1,
  "co 7 Us": 1,
  "Moincht": 1,
  "de Castello-": 1,
  "Lune": 1,
  "Consacr\u00e9e": 1,
  "WiLMIiNA": 1,
  "Jamais": 1,
  "Souffrez": 1,
  "A RS": 1,
  "p\u00e9nitens\n\n": 1,
  "nelle": 1,
  "Soinsde l\u2019": 1,
  "Kk\u00e9s": 1,
  "cau": 1,
  "c\u0153t": 1,
  "Lens": 1,
  "Almina": 1,
  "t\u2019": 1,
  "C\u00e9zarins": 1,
  "Disons": 1,
  "C\u00e9zarimi": 1,
  "\u00cf": 1,
  "\u00ceve": 1,
  "Ten": 1,
  "Maria": 1,
  "rivi\u00e8re n\u2019": 1,
  "Adriatique": 1,
  "taillis": 1,
  "-.": 1,
  "r\u00e9pliquai-je": 1,
  "m\u00e9mcton,}e": 1,
  "doux": 1,
  "RS": 1,
  "mand": 1,
  "W1LMINA": 1,
  "terre": 1,
  "Lihiietan": 1,
  "Chain\u00e9": 1,
  "Je l\u2019eusse interrompu": 1,
  "OT": 1,
  "st long-temps": 1,
  "Alter-": 1,
  "Lyon": 1,
  "Alpes": 1,
  "ac=": 1,
  "Jaterre": 1,
  "Malvima": 1,
  "Painour": 1,
  "Ste": 1,
  "PA\n\na SPF": 1,
  "Lonjours": 1,
  "\u00celes d\u00e9tails\n\u2018": 1,
  "L\u00e9rinde": 1,
  "France": 1,
  "Espagne": 1,
  "Mara": 1,
  "U": 1,
  "ET A": 1,
  "Ja nourrir": 1,
  "consen--": 1,
  "Cirlos": 1,
  "L\u00e9rinse": 1,
  "Jarimes": 1,
  "Insens\u00e9": 1,
  "b\u00e9nis": 1,
  "\u00celes environs de ma\nchaumi\u00e8re": 1,
  "Trem-": 1,
  "Be Crus": 1,
  "Veuez": 1,
  "conduisez-inot": 1,
  "Fr": 1,
  "lalie": 1,
  "\\WYILMINA": 1,
  "Vis": 1,
  "She -\n": 1,
  "Am\u00e9rique": 1,
  "Indes orientales": 1,
  "u\u2019": 1,
  "Arr\u00eatez": 1,
  "Je l\u2019\u00e9coutais": 1,
  "Ine\u00f1fit": 1,
  "Sance": 1,
  "Italie": 1,
  "St 7 \u2018\npren": 1,
  "cap de\nBonne-Esp\u00e9rance": 1,
  "haitais": 1,
  "Fr\n\nWILMINA": 1,
  "Afrique": 1,
  "Cafrerie": 1,
  "Cafres": 1,
  "Europ\u00e9en": 1,
  "Cap-de-Bonne-Esp\u00e9rance": 1,
  "Angleterre": 1,
  "A\u00eflons": 1,
  "e\u2019": 1,
  "A pennins": 1,
  "WILMIiNA": 1,
  "Jeles": 1,
  "repais-1o1": 1,
  "Liens": 1,
  "CO": 1,
  "Faune": 1,
  "Dans l\u2019": 1,
  "Phabit": 1,
  "ch\u00e2timens": 1,
  "Sup\u00e9rieur": 1,
  "rafraichissemens": 1,
  "Alm\u00e9rano": 1,
  "Cri": 1,
  "Llemps": 1,
  "C\u00e9zariai": 1,
  "\u00celes ma\u00efheurs": 1,
  "A\u00efberu": 1,
  "Leschoses": 1,
  "Wiimina": 1,
  "doctenr Cornetti": 1,
  "Apernins": 1,
  "Ja v\u00e9nerable Bianchi": 1,
  "\u00celes": 1,
  "Ti": 1,
  "nouvela l\u2019": 1,
  "Alshonse": 1,
  "Pe\u00a3-": 1,
  "Eternel": 1,
  "\u00e9cria-t-ilenfin": 1,
  "Albmo": 1,
  "W\u00e4lmino": 1,
  "Canton": 1,
  "Vais": 1,
  "Vext\u00e9rieur": 1,
  "La Anse Es": 1,
  "FL": 1,
  "Pea": 1,
  "B": 1,
  "Abe": 1,
  "F\n\n": 1,
  "Maresco.\u2014Signor": 1,
  "Anennins": 1,
  "manda": 1,
  "san": 1,
  "Ca A": 1,
  "F 4 F": 1,
  "-$ L": 1,
  "Sit\u00f4t": 1,
  "Les": 1,
  "DCE": 1,
  "Lo": 1,
  "er": 1
}